[
    {
        "id": "3228-bencana-peperangan-akhir-zaman",
        "id_drive": "1pU0qoJizbXfvR2Ety-HBvzjYDWx9za1O",
        "title": "Bencana & Peperangan Akhir Zaman",
        "author": "-",
        "category": "Islam & Spiritual",
        "description": "E-book PDF dari Google Drive — kategori Islam & Spiritual."
    },
    {
        "id": "achmad-syahid-buku-diskursus-psikologi-islam",
        "id_drive": "1PL15GbmEXzdrNczYSptGNYFY0uP1cOHf",
        "title": "Buku Diskursus_Psikologi Islam",
        "author": "Achmad Syahid",
        "category": "Islam & Spiritual",
        "description": "E-book PDF dari Google Drive — kategori Islam & Spiritual."
    },
    {
        "id": "buku-psikologi-agama-psikologi-islami",
        "id_drive": "1SvDlUUNtCXD8kLMd-xGc50i0zuYuiwOE",
        "title": "BUKU PSIKOLOGI AGAMA & PSIKOLOGI ISLAMI",
        "author": "-",
        "category": "Islam & Spiritual",
        "description": "E-book PDF dari Google Drive — kategori Islam & Spiritual."
    },
    {
        "id": "148-marketing-hebat-ala-rasulullah-saw-faidatur-robiah",
        "id_drive": "1VbeCQs8wvzH1ijbGMWZx0iZ7JglckW4D",
        "title": "Faidatur Robiah",
        "author": "Marketing Hebat Ala Rasulullah SAW",
        "category": "Islam & Spiritual",
        "description": "E-book PDF dari Google Drive — kategori Islam & Spiritual."
    },
    {
        "id": "2701-sirah-nabawiyah-ibnu-hisyam",
        "id_drive": "1rEZWU58Z2YoIUbbarYXvTku-bnQK6IUO",
        "title": "Ibnu Hisyam",
        "author": "Sirah Nabawiyah",
        "category": "Islam & Spiritual",
        "description": "E-book PDF dari Google Drive — kategori Islam & Spiritual."
    },
    {
        "id": "pdfcoffee-com-prioritas-antara-adab-dan-ilmu-pdf-free",
        "id_drive": "1aKzGRl2gNNHLmyW9bFTKxV_Rm6905DWA",
        "title": "pdfcoffee.com_prioritas-antara-adab-dan-ilmu-pdf-free",
        "author": "-",
        "category": "Islam & Spiritual",
        "description": "E-book PDF dari Google Drive — kategori Islam & Spiritual."
    },
    {
        "id": "psikologi-islam",
        "id_drive": "1ApeLo6CJ87FxDd2b2q-3Flb4ws6-SH1i",
        "title": "psikologi islam",
        "author": "-",
        "category": "Islam & Spiritual",
        "description": "E-book PDF dari Google Drive — kategori Islam & Spiritual."
    },
    {
        "id": "quranic-law-of-attraction",
        "id_drive": "1lfhKRhRIymTA5qTSRcmXnG461_uVx86u",
        "title": "Quranic Law of Attraction",
        "author": "-",
        "category": "Islam & Spiritual",
        "description": "E-book PDF dari Google Drive — kategori Islam & Spiritual."
    },
    {
        "id": "sirah-nabawiyah-ibnu-hisyam-lengkap",
        "id_drive": "1qef0dehAbnAsmEiqWSAHdZrLwnDgXMcb",
        "title": "Sirah Nabawiyah Ibnu Hisyam (lengkap)",
        "author": "-",
        "category": "Islam & Spiritual",
        "description": "E-book PDF dari Google Drive — kategori Islam & Spiritual."
    },
    {
        "id": "2645-ya-allah-aku-pulang",
        "id_drive": "1a-dZ2jGZ_mfYgiYL4dqRBjTukvkcATEU",
        "title": "Ya Allah aku pulang",
        "author": "-",
        "category": "Islam & Spiritual",
        "description": "E-book PDF dari Google Drive — kategori Islam & Spiritual."
    },
    {
        "id": "e-6611-10-ways-to-change-your-mindset-right-now-mel-robbins-b-indo",
        "id_drive": "1g6gONXFeW9qpMZlj4CeiuEyI_WnZcoss",
        "title": "10 Ways To Change Your Mindset Right Now",
        "author": "Mel Robbins (B. INDO)",
        "category": "Psikologi",
        "description": "E-book PDF dari Google Drive — kategori Psikologi."
    },
    {
        "id": "e-6208-mindset-by-carol-s-dweck-1",
        "id_drive": "17zFlApgn9f6W1oHnk6HRyiMzXoFURsS3",
        "title": "Mindset",
        "author": "Carol S Dweck 1",
        "category": "Psikologi",
        "description": "E-book PDF dari Google Drive — kategori Psikologi."
    },
    {
        "id": "e-2586-rahasia-menghancurkan-mental-block-1",
        "id_drive": "1iIbMpzo1MAQbVYFs5FFTpR1Gg2t213lO",
        "title": "Rahasia Menghancurkan Mental Block",
        "author": "-",
        "category": "Psikologi",
        "description": "E-book PDF dari Google Drive — kategori Psikologi."
    },
    {
        "id": "the-psychology-of-money-morgan-housel-bahasa",
        "id_drive": "1bb4-V_rTZo-CmKl5L05mCSqcsMuOxikD",
        "title": "The Psychology of Money (Morgan Housel) BAHASA",
        "author": "-",
        "category": "Psikologi",
        "description": "E-book PDF dari Google Drive — kategori Psikologi."
    },
    {
        "id": "807-50-law-of-attraction-exercises-tips-b-indonesia",
        "id_drive": "1xjZWbf57aLFKFHgcBeqX6JS6KPs6xDk0",
        "title": "50 Law of Attraction Exercises, Tips & b.indonesia",
        "author": "-",
        "category": "Motivasi & Pengembangan Diri",
        "description": "E-book PDF dari Google Drive — kategori Motivasi & Pengembangan Diri."
    },
    {
        "id": "3434-personal-attraction-agar-siapa-pun-tertarik-kepada-anda-dan-tidak-bisa-menolak-anda",
        "id_drive": "1gqm1XgFcUAO170IH9lk5tp9kxZSPQz8g",
        "title": "Agar Siapa Pun Tertarik Kepada Anda dan Tidak Bisa Menolak Anda",
        "author": "Personal Attraction",
        "category": "Motivasi & Pengembangan Diri",
        "description": "E-book PDF dari Google Drive — kategori Motivasi & Pengembangan Diri."
    },
    {
        "id": "e-6606-atomic-habits-bahasa-indonesia-perubahan-kecil-yang-memberikan-hasil-luar-biasa-by-james-clear",
        "id_drive": "1OxfT73Gkhhci3N3dKEHNMuYFzNsgRbpX",
        "title": "Atomic Habits - Perubahan Kecil Yang Memberikan Hasil Luar Biasa",
        "author": "James Clear",
        "category": "Motivasi & Pengembangan Diri",
        "description": "E-book PDF dari Google Drive — kategori Motivasi & Pengembangan Diri."
    },
    {
        "id": "e-5532-good-vibes-good-life-how-self-love-is-the-key-to-unlocking-your-greatness-life-bahasa-indonesia",
        "id_drive": "1NLW55-2cFYwo3dJV0ikeGXFy8HdVRH1E",
        "title": "Good Vibes, Good Life How Self-Love Is The Key To Unlocking Your Greatness Life",
        "author": "Bahasa Indonesia",
        "category": "Motivasi & Pengembangan Diri",
        "description": "E-book PDF dari Google Drive — kategori Motivasi & Pengembangan Diri."
    },
    {
        "id": "e-8346-hidup-antigalau-menata-karir-dan-masa-depan-di-umur-20an",
        "id_drive": "1nm56lktr1eNhdgz_ibi571uH9X3FtwOI",
        "title": "Hidup Antigalau Menata Karir Dan Masa Depan Di Umur 20An",
        "author": "-",
        "category": "Motivasi & Pengembangan Diri",
        "description": "E-book PDF dari Google Drive — kategori Motivasi & Pengembangan Diri."
    },
    {
        "id": "e-7660-rehat-dulu-belajar-sembuh-seiring-tumbuh-by-syahid-muhammad",
        "id_drive": "1YaTm50DXC4FLXPDMp1ncKr6I5IYesHU2",
        "title": "Rehat Dulu Belajar Sembuh -Seiring Tumbuh",
        "author": "Syahid Muhammad",
        "category": "Motivasi & Pengembangan Diri",
        "description": "E-book PDF dari Google Drive — kategori Motivasi & Pengembangan Diri."
    },
    {
        "id": "e-3956-seni-hidup-minimalis-petunjuk-minimalis-menuju-hidup-yang-apik-tertata-dan-sederhana-francine-jay",
        "id_drive": "1xVbIwwLrAwRynza8zUM6WrkfSSSsg61S",
        "title": "Seni Hidup Minimalis; Petunjuk Minimalis Menuju Hidup Yang Apik, Tertata, Dan Sederhana",
        "author": "Francine Jay",
        "category": "Motivasi & Pengembangan Diri",
        "description": "E-book PDF dari Google Drive — kategori Motivasi & Pengembangan Diri."
    },
    {
        "id": "e-6604-baca-buku-ini-saat-engkau-gagal-sesungguhnya-berpura-pura-sukses-itu-melelahkan",
        "id_drive": "1KYWEV5do1p9La9kgvqlRXLCNQ6rE8BVA",
        "title": "Sesungguhnya Berpura Pura Sukses Itu Melelahkan",
        "author": "Baca Buku Ini Saat Engkau Gagal",
        "category": "Motivasi & Pengembangan Diri",
        "description": "E-book PDF dari Google Drive — kategori Motivasi & Pengembangan Diri."
    },
    {
        "id": "543-tenang-semua-akan-baik-baik-saja",
        "id_drive": "1w2yZOSoJkXUx3E-P5rPkfIERlnfnA8G-",
        "title": "Tenang, Semua Akan Baik-Baik Saja",
        "author": "-",
        "category": "Motivasi & Pengembangan Diri",
        "description": "E-book PDF dari Google Drive — kategori Motivasi & Pengembangan Diri."
    },
    {
        "id": "e-8598-titik-terendah-by-priaseratuspersen",
        "id_drive": "12Eo0EycTFBLAU6JUwgi-E0Kqi4XuIW4S",
        "title": "Titik Terendah",
        "author": "Priaseratuspersen",
        "category": "Motivasi & Pengembangan Diri",
        "description": "E-book PDF dari Google Drive — kategori Motivasi & Pengembangan Diri."
    },
    {
        "id": "e-2581-uzrah-the-habit-of-critical-thinking-powerful-routines-to-change-your-mind-and-sharpen-your-thinking",
        "id_drive": "1PnhmpKv6LSDPwT6ztaSlLqaFxSbXhqj2",
        "title": "Uzrah The Habit Of Critical Thinking Powerful Routines To Change Your Mind And Sharpen Your Thinking",
        "author": "-",
        "category": "Motivasi & Pengembangan Diri",
        "description": "E-book PDF dari Google Drive — kategori Motivasi & Pengembangan Diri."
    },
    {
        "id": "e-2746-business-plan-bagaimana-memulai-menjalankan-bisnis-baru",
        "id_drive": "15dptvrrww8iqdnwoOsKVc1ixYq7RZmrx",
        "title": "Business Plan Bagaimana Memulai Menjalankan Bisnis Baru",
        "author": "-",
        "category": "Bisnis & Keuangan",
        "description": "E-book PDF dari Google Drive — kategori Bisnis & Keuangan."
    },
    {
        "id": "kitab-money-from-tiktok",
        "id_drive": "19nrifdjbXXUceVCo705ew5ZHQ1O82suZ",
        "title": "Kitab money from tiktok",
        "author": "-",
        "category": "Bisnis & Keuangan",
        "description": "E-book PDF dari Google Drive — kategori Bisnis & Keuangan."
    },
    {
        "id": "e-8112-mengelola-gaji-bulanan-mra-media",
        "id_drive": "1hfwXZc2DPgvpG9ONjB-QGiAgMInMxAef",
        "title": "Mengelola Gaji Bulanan Mra Media",
        "author": "-",
        "category": "Bisnis & Keuangan",
        "description": "E-book PDF dari Google Drive — kategori Bisnis & Keuangan."
    },
    {
        "id": "e-5219-the-master-book-of-personal-branding-farco-siswiyanto-raharjo",
        "id_drive": "16hsTRKR7SnTOZkuudXy1mhhwZQucyawg",
        "title": "The Master Book Of Personal Branding Farco Siswiyanto Raharjo",
        "author": "-",
        "category": "Bisnis & Keuangan",
        "description": "E-book PDF dari Google Drive — kategori Bisnis & Keuangan."
    },
    {
        "id": "2321-falsafah-kepemimpinan-jawa-by-dr-suwardi-endraswara-m-hum",
        "id_drive": "1sQUBa4N4qcf97UM3SfqrgTlfHDYzNcy5",
        "title": "Falsafah Kepemimpinan Jawa",
        "author": "Dr. Suwardi Endraswara, M.Hum",
        "category": "Kepemimpinan",
        "description": "E-book PDF dari Google Drive — kategori Kepemimpinan."
    },
    {
        "id": "e-1458-the-principles-of-power-dion-yulianto-rahasia-memanipulasi-orang-lain",
        "id_drive": "1NJwXy_Pk_NUwn3q7gYTFA9zLWYyUZD3t",
        "title": "Rahasia Memanipulasi Orang Lain",
        "author": "The Principles Of Power Dion Yulianto",
        "category": "Kepemimpinan",
        "description": "E-book PDF dari Google Drive — kategori Kepemimpinan."
    },
    {
        "id": "3301-the-principles-of-power-dion-yulianto",
        "id_drive": "1jXTMlmEwEyAUXWxc1DSxLex0Y0d-I11A",
        "title": "The Principles Of Power (Dion Yulianto)",
        "author": "-",
        "category": "Kepemimpinan",
        "description": "E-book PDF dari Google Drive — kategori Kepemimpinan."
    },
    {
        "id": "filosofi-teras-by-henry-manampiring",
        "id_drive": "1kl7-Y6a7CwoJk6TQ93vRy3C86mLvBZ_9",
        "title": "Filosofi Teras",
        "author": "Henry Manampiring",
        "category": "Filosofi & Berpikir",
        "description": "E-book PDF dari Google Drive — kategori Filosofi & Berpikir."
    },
    {
        "id": "3527-filsafat-berpikir-teknik-teknik-berpikir-logis-kontra-kesesatan-berpikir-ainur-rahman-hidayat",
        "id_drive": "10wdJX5M_QA9S9RrLzQM8mUP_IBNtDleA",
        "title": "Filsafat Berpikir Teknik-Teknik Berpikir Logis Kontra Kesesatan Berpikir (Ainur Rahman Hidayat)",
        "author": "-",
        "category": "Filosofi & Berpikir",
        "description": "E-book PDF dari Google Drive — kategori Filosofi & Berpikir."
    },
    {
        "id": "2991-masukan-ke-bundel-berbicara-seni-berbicara-kepada-siapa-saja-kapan-saja-di-mana-saja-by-larry-king",
        "id_drive": "1EjX3iW33RHQK5mD4XxO5ZV5i5EFs3YZ6",
        "title": "Seni Berbicara kepada Siapa Saja, Kapan Saja, di Mana Saja",
        "author": "Larry King",
        "category": "Komunikasi",
        "description": "E-book PDF dari Google Drive — kategori Komunikasi."
    },
    {
        "id": "e-8494-seni-berbicara-tanpa-bikin-sakit-hati-by-oh-su-hyang",
        "id_drive": "1YZrcxvpGBElHTrB2j8tXjBNithsGg9ae",
        "title": "Seni Berbicara Tanpa Bikin Sakit Hati",
        "author": "Oh Su Hyang",
        "category": "Komunikasi",
        "description": "E-book PDF dari Google Drive — kategori Komunikasi."
    },
    {
        "id": "sejarah-dunia-yang-disembunyikan",
        "id_drive": "14oYoZJzunwSRrVpmMJ4CWbXRGUfAkCmT",
        "title": "Sejarah-Dunia-yang-Disembunyikan",
        "author": "-",
        "category": "Sejarah",
        "description": "E-book PDF dari Google Drive — kategori Sejarah."
    },
    {
        "id": "e-4539-101-best-microsoft-excel-tips-tricks",
        "id_drive": "1oMGR-xClc0URRnShXPpzUecNMefb3wgE",
        "title": "101 Best Microsoft Excel Tips Tricks",
        "author": "-",
        "category": "Teknologi & Skill",
        "description": "E-book PDF dari Google Drive — kategori Teknologi & Skill."
    },
    {
        "id": "e-3635-kenali-musuhmu-yang-tak-terlihatdan-kalahkan-mereka",
        "id_drive": "1PwIwdWxr5p0_Wr9LC7j8oINpRN2Tnu6d",
        "title": "Kenali Musuhmu Yang Tak Terlihatdan Kalahkan Mereka",
        "author": "-",
        "category": "Umum",
        "description": "E-book PDF dari Google Drive — kategori Umum."
    }
]
